{
  "mnt_id": 40,
  "mnt_name": "백덕산",
  "course_id": 102,
  "max_ele": 1301.003,
  "total_length_km": "8.3km",
  "total_time": "1시간 44분",
  "start_name": "백덕산 주차창",
  "end_name": "먹골정류소",
  "level": "상",
  "course_name": "거친산길 코스",
  "min_ele": 0.0,
  "track": [
    {
      "path_id": 0,
      "path": [
        {
          "lat": 37.428032,
          "lng": 128.298828,
          "ele": 619.815
        },
        {
          "lat": 37.422642,
          "lng": 128.30127,
          "ele": 639.75
        }
      ],
      "color": "#c44745",
      "start_name": "백덕산 주차창",
      "end_name": "백덕산 등산로 입구. 먹골",
      "length_meter": 637.0,
      "time_minute": 7
    },
    {
      "path_id": 1,
      "path": [
        {
          "lat": 37.422642,
          "lng": 128.30127,
          "ele": 639.75
        },
        {
          "lat": 37.414425,
          "lng": 128.304306,
          "ele": 767.256
        }
      ],
      "color": "#0a8604",
      "start_name": "백덕산 등산로 입구. 먹골",
      "end_name": "고목이 쓰러져 터널처럼 형성",
      "length_meter": 952.2,
      "time_minute": 11
    },
    {
      "path_id": 2,
      "path": [
        {
          "lat": 37.414425,
          "lng": 128.304306,
          "ele": 767.256
        },
        {
          "lat": 37.411236,
          "lng": 128.306732,
          "ele": 854.727
        }
      ],
      "color": "#a7a850",
      "start_name": "고목이 쓰러져 터널처럼 형성",
      "end_name": "갈림길",
      "length_meter": 414.3,
      "time_minute": 5
    },
    {
      "path_id": 3,
      "path": [
        {
          "lat": 37.411236,
          "lng": 128.306732,
          "ele": 854.727
        },
        {
          "lat": 37.407688,
          "lng": 128.308105,
          "ele": 967.727
        }
      ],
      "color": "#24b332",
      "start_name": "갈림길",
      "end_name": "이정표옆 작은 쉼터",
      "length_meter": 412.7,
      "time_minute": 5
    },
    {
      "path_id": 4,
      "path": [
        {
          "lat": 37.407688,
          "lng": 128.308105,
          "ele": 967.727
        },
        {
          "lat": 37.406456,
          "lng": 128.305237,
          "ele": 1065.233
        }
      ],
      "color": "#4587c6",
      "start_name": "이정표옆 작은 쉼터 / 철쭉군락지 안내",
      "end_name": "등산로 폐쇄",
      "length_meter": 288.2,
      "time_minute": 4
    },
    {
      "path_id": 5,
      "path": [
        {
          "lat": 37.406456,
          "lng": 128.305237,
          "ele": 1065.233
        },
        {
          "lat": 37.404129,
          "lng": 128.302078,
          "ele": 1134.774
        }
      ],
      "color": "#b47732",
      "start_name": "등산로 폐쇄",
      "end_name": "길옆 작은 공터",
      "length_meter": 380.5,
      "time_minute": 4
    },
    {
      "path_id": 6,
      "path": [
        {
          "lat": 37.404129,
          "lng": 128.302078,
          "ele": 1134.774
        },
        {
          "lat": 37.404133,
          "lng": 128.302017,
          "ele": 1142.544
        }
      ],
      "color": "#334e6d",
      "start_name": "길옆 작은 공터",
      "end_name": "작은 공터 둥근 의자",
      "length_meter": 5.4,
      "time_minute": 0
    },
    {
      "path_id": 7,
      "path": [
        {
          "lat": 37.404133,
          "lng": 128.302017,
          "ele": 1142.544
        },
        {
          "lat": 37.402382,
          "lng": 128.296631,
          "ele": 1240.42
        }
      ],
      "color": "#689219",
      "start_name": "작은 공터 둥근 의자",
      "end_name": "갈림길",
      "length_meter": 514.1,
      "time_minute": 6
    },
    {
      "path_id": 8,
      "path": [
        {
          "lat": 37.402382,
          "lng": 128.296631,
          "ele": 1240.42
        },
        {
          "lat": 37.401268,
          "lng": 128.295212,
          "ele": 1301.003
        }
      ],
      "color": "#0e7688",
      "start_name": "갈림길",
      "end_name": "고목 쓰러짐",
      "length_meter": 176.2,
      "time_minute": 2
    },
    {
      "path_id": 9,
      "path": [
        {
          "lat": 37.401268,
          "lng": 128.295212,
          "ele": 1301.003
        },
        {
          "lat": 37.413788,
          "lng": 128.291061,
          "ele": 1017.868
        }
      ],
      "color": "#9c1fbc",
      "start_name": "고목 쓰러짐",
      "end_name": "경사가 급하고 흙길이라 주의",
      "length_meter": 1439.6,
      "time_minute": 17
    },
    {
      "path_id": 10,
      "path": [
        {
          "lat": 37.413788,
          "lng": 128.291061,
          "ele": 1017.868
        },
        {
          "lat": 37.421379,
          "lng": 128.286163,
          "ele": 731.528
        }
      ],
      "color": "#577128",
      "start_name": "경사가 급하고 흙길이라 주의 / 갈림길",
      "end_name": "백덕산 등산로입구",
      "length_meter": 951.4,
      "time_minute": 15
    },
    {
      "path_id": 11,
      "path": [
        {
          "lat": 37.421379,
          "lng": 128.286163,
          "ele": 731.528
        },
        {
          "lat": 37.430496,
          "lng": 128.284485,
          "ele": 0.0
        }
      ],
      "color": "#4a5e94",
      "start_name": "백덕산 등산로입구",
      "end_name": "운교정류장",
      "length_meter": 1024.5,
      "time_minute": 12
    },
    {
      "path_id": 12,
      "path": [
        {
          "lat": 37.430496,
          "lng": 128.284485,
          "ele": 0.0
        },
        {
          "lat": 37.429455,
          "lng": 128.286102,
          "ele": 641.554
        }
      ],
      "color": "#8f6d27",
      "start_name": "운교정류장",
      "end_name": "운교1리 마을 회관 앞 화장실",
      "length_meter": 183.8,
      "time_minute": 2
    },
    {
      "path_id": 13,
      "path": [
        {
          "lat": 37.429455,
          "lng": 128.286102,
          "ele": 641.554
        },
        {
          "lat": 37.433681,
          "lng": 128.295547,
          "ele": 566.786
        }
      ],
      "color": "#559592",
      "start_name": "운교1리 마을 회관 앞 화장실 / 웨이포인트 31",
      "end_name": "먹골정류소",
      "length_meter": 957.5,
      "time_minute": 15
    }
  ]
}