{
  "mnt_id": 66,
  "mnt_name": "월출산",
  "course_id": 184,
  "max_ele": 745.0,
  "total_length_km": "6.2km",
  "total_time": "1시간 17분",
  "start_name": "월출산 도갑사주차장화장실",
  "end_name": "목구조목",
  "level": "중",
  "course_name": "탄력등산 코스",
  "min_ele": 105.0,
  "track": [
    {
      "path_id": 0,
      "path": [
        {
          "lat": 34.75597,
          "lng": 126.657715,
          "ele": 129.0
        },
        {
          "lat": 34.753788,
          "lng": 126.660568,
          "ele": 105.0
        }
      ],
      "color": "#9a8db4",
      "start_name": "월출산 도갑사주차장화장실 / 도갑사주차장화장실 / 월출산 도갑시코스 입구",
      "end_name": "보호수",
      "length_meter": 360.8,
      "time_minute": 6
    },
    {
      "path_id": 1,
      "path": [
        {
          "lat": 34.753788,
          "lng": 126.660568,
          "ele": 105.0
        },
        {
          "lat": 34.753578,
          "lng": 126.660126,
          "ele": 108.0
        }
      ],
      "color": "#1985bf",
      "start_name": "보호수",
      "end_name": "대중교통승강장",
      "length_meter": 46.6,
      "time_minute": 0
    },
    {
      "path_id": 2,
      "path": [
        {
          "lat": 34.753578,
          "lng": 126.660126,
          "ele": 108.0
        },
        {
          "lat": 34.752819,
          "lng": 126.661987,
          "ele": 111.0
        }
      ],
      "color": "#730c3b",
      "start_name": "대중교통승강장 / 갈림길",
      "end_name": "도갑사 해탈문",
      "length_meter": 214.9,
      "time_minute": 3
    },
    {
      "path_id": 3,
      "path": [
        {
          "lat": 34.752819,
          "lng": 126.661987,
          "ele": 111.0
        },
        {
          "lat": 34.75325,
          "lng": 126.663704,
          "ele": 123.0
        }
      ],
      "color": "#4bb233",
      "start_name": "도갑사 해탈문 / 도갑사",
      "end_name": "탐방로입구",
      "length_meter": 171.4,
      "time_minute": 2
    },
    {
      "path_id": 4,
      "path": [
        {
          "lat": 34.75325,
          "lng": 126.663704,
          "ele": 123.0
        },
        {
          "lat": 34.753757,
          "lng": 126.664177,
          "ele": 121.0
        }
      ],
      "color": "#49961a",
      "start_name": "탐방로입구 / 입구",
      "end_name": "목구조목",
      "length_meter": 71.8,
      "time_minute": 1
    },
    {
      "path_id": 5,
      "path": [
        {
          "lat": 34.753757,
          "lng": 126.664177,
          "ele": 121.0
        },
        {
          "lat": 34.754303,
          "lng": 126.66526,
          "ele": 133.0
        }
      ],
      "color": "#7f8810",
      "start_name": "목구조목 / 도갑사계곡",
      "end_name": "도선국사비각",
      "length_meter": 117.3,
      "time_minute": 1
    },
    {
      "path_id": 6,
      "path": [
        {
          "lat": 34.754303,
          "lng": 126.66526,
          "ele": 133.0
        },
        {
          "lat": 34.753014,
          "lng": 126.668549,
          "ele": 164.0
        }
      ],
      "color": "#7ab73c",
      "start_name": "도선국사비각",
      "end_name": "목구조목",
      "length_meter": 332.9,
      "time_minute": 4
    },
    {
      "path_id": 7,
      "path": [
        {
          "lat": 34.753014,
          "lng": 126.668549,
          "ele": 164.0
        },
        {
          "lat": 34.7533,
          "lng": 126.686104,
          "ele": 563.0
        }
      ],
      "color": "#3d781a",
      "start_name": "목구조목",
      "end_name": "갈림길",
      "length_meter": 1604.1,
      "time_minute": 20
    },
    {
      "path_id": 8,
      "path": [
        {
          "lat": 34.7533,
          "lng": 126.686104,
          "ele": 563.0
        },
        {
          "lat": 34.753971,
          "lng": 126.68692,
          "ele": 577.0
        }
      ],
      "color": "#93c19b",
      "start_name": "갈림길 / 억새밭 전망대",
      "end_name": "목구조목",
      "length_meter": 115.1,
      "time_minute": 1
    },
    {
      "path_id": 9,
      "path": [
        {
          "lat": 34.753971,
          "lng": 126.68692,
          "ele": 577.0
        },
        {
          "lat": 34.754187,
          "lng": 126.688411,
          "ele": 586.0
        }
      ],
      "color": "#2b985d",
      "start_name": "목구조목",
      "end_name": "웨이포인트 25",
      "length_meter": 138.3,
      "time_minute": 1
    },
    {
      "path_id": 10,
      "path": [
        {
          "lat": 34.754187,
          "lng": 126.688411,
          "ele": 586.0
        },
        {
          "lat": 34.754517,
          "lng": 126.689453,
          "ele": 606.0
        }
      ],
      "color": "#92babd",
      "start_name": "웨이포인트 25",
      "end_name": "목구조목",
      "length_meter": 102.0,
      "time_minute": 1
    },
    {
      "path_id": 11,
      "path": [
        {
          "lat": 34.754517,
          "lng": 126.689453,
          "ele": 606.0
        },
        {
          "lat": 34.755451,
          "lng": 126.690765,
          "ele": 634.0
        }
      ],
      "color": "#9799b9",
      "start_name": "목구조목",
      "end_name": "갈림길",
      "length_meter": 158.6,
      "time_minute": 1
    },
    {
      "path_id": 12,
      "path": [
        {
          "lat": 34.755451,
          "lng": 126.690765,
          "ele": 634.0
        },
        {
          "lat": 34.757484,
          "lng": 126.692833,
          "ele": 686.0
        }
      ],
      "color": "#030fa5",
      "start_name": "갈림길 / 목구조목",
      "end_name": "향로봉",
      "length_meter": 298.6,
      "time_minute": 4
    },
    {
      "path_id": 13,
      "path": [
        {
          "lat": 34.757484,
          "lng": 126.692833,
          "ele": 686.0
        },
        {
          "lat": 34.759281,
          "lng": 126.692719,
          "ele": 723.0
        }
      ],
      "color": "#153c17",
      "start_name": "향로봉",
      "end_name": "갈림길",
      "length_meter": 200.1,
      "time_minute": 2
    },
    {
      "path_id": 14,
      "path": [
        {
          "lat": 34.759281,
          "lng": 126.692719,
          "ele": 723.0
        },
        {
          "lat": 34.760395,
          "lng": 126.693642,
          "ele": 716.0
        }
      ],
      "color": "#27388c",
      "start_name": "갈림길",
      "end_name": "목구조목",
      "length_meter": 149.8,
      "time_minute": 1
    },
    {
      "path_id": 15,
      "path": [
        {
          "lat": 34.760395,
          "lng": 126.693642,
          "ele": 716.0
        },
        {
          "lat": 34.761494,
          "lng": 126.693703,
          "ele": 720.0
        }
      ],
      "color": "#c0b20b",
      "start_name": "목구조목",
      "end_name": "갈림길",
      "length_meter": 122.3,
      "time_minute": 1
    },
    {
      "path_id": 16,
      "path": [
        {
          "lat": 34.761494,
          "lng": 126.693703,
          "ele": 720.0
        },
        {
          "lat": 34.761646,
          "lng": 126.694061,
          "ele": 731.0
        }
      ],
      "color": "#344006",
      "start_name": "갈림길",
      "end_name": "구정봉",
      "length_meter": 36.8,
      "time_minute": 0
    },
    {
      "path_id": 17,
      "path": [
        {
          "lat": 34.761646,
          "lng": 126.694061,
          "ele": 731.0
        },
        {
          "lat": 34.762775,
          "lng": 126.692497,
          "ele": 677.0
        }
      ],
      "color": "#2e3609",
      "start_name": "구정봉",
      "end_name": "갈림길",
      "length_meter": 190.2,
      "time_minute": 2
    },
    {
      "path_id": 18,
      "path": [
        {
          "lat": 34.762775,
          "lng": 126.692497,
          "ele": 677.0
        },
        {
          "lat": 34.763393,
          "lng": 126.691986,
          "ele": 664.0
        }
      ],
      "color": "#7a7419",
      "start_name": "갈림길 / 웨이포인트 48",
      "end_name": "목구조목",
      "length_meter": 84.5,
      "time_minute": 1
    },
    {
      "path_id": 19,
      "path": [
        {
          "lat": 34.763393,
          "lng": 126.691986,
          "ele": 664.0
        },
        {
          "lat": 34.764122,
          "lng": 126.690628,
          "ele": 652.0
        }
      ],
      "color": "#2d7554",
      "start_name": "목구조목",
      "end_name": "갈림길",
      "length_meter": 148.2,
      "time_minute": 1
    },
    {
      "path_id": 20,
      "path": [
        {
          "lat": 34.764122,
          "lng": 126.690628,
          "ele": 652.0
        },
        {
          "lat": 34.763916,
          "lng": 126.690514,
          "ele": 609.0
        }
      ],
      "color": "#618360",
      "start_name": "갈림길 / 목구조목",
      "end_name": "마애여래좌상",
      "length_meter": 27.2,
      "time_minute": 0
    },
    {
      "path_id": 21,
      "path": [
        {
          "lat": 34.763916,
          "lng": 126.690514,
          "ele": 609.0
        },
        {
          "lat": 34.764591,
          "lng": 126.689751,
          "ele": 599.0
        }
      ],
      "color": "#6d4e19",
      "start_name": "마애여래좌상 / 갈림길",
      "end_name": "삼층석탑",
      "length_meter": 106.1,
      "time_minute": 1
    },
    {
      "path_id": 22,
      "path": [
        {
          "lat": 34.764591,
          "lng": 126.689751,
          "ele": 599.0
        },
        {
          "lat": 34.763476,
          "lng": 126.691813,
          "ele": 659.0
        }
      ],
      "color": "#3896aa",
      "start_name": "삼층석탑",
      "end_name": "웨이포인트 46",
      "length_meter": 225.5,
      "time_minute": 2
    },
    {
      "path_id": 23,
      "path": [
        {
          "lat": 34.763476,
          "lng": 126.691813,
          "ele": 659.0
        },
        {
          "lat": 34.760826,
          "lng": 126.69429,
          "ele": 693.0
        }
      ],
      "color": "#a3079f",
      "start_name": "웨이포인트 46 / 웨이포인트 47",
      "end_name": "배틀굴",
      "length_meter": 371.5,
      "time_minute": 6
    },
    {
      "path_id": 24,
      "path": [
        {
          "lat": 34.760826,
          "lng": 126.69429,
          "ele": 693.0
        },
        {
          "lat": 34.760644,
          "lng": 126.69636,
          "ele": 658.0
        }
      ],
      "color": "#852269",
      "start_name": "배틀굴",
      "end_name": "웨이포인트 50",
      "length_meter": 190.2,
      "time_minute": 2
    },
    {
      "path_id": 25,
      "path": [
        {
          "lat": 34.760644,
          "lng": 126.69636,
          "ele": 658.0
        },
        {
          "lat": 34.761196,
          "lng": 126.697639,
          "ele": 617.0
        }
      ],
      "color": "#0337a4",
      "start_name": "웨이포인트 50",
      "end_name": "갈림길",
      "length_meter": 132.0,
      "time_minute": 1
    },
    {
      "path_id": 26,
      "path": [
        {
          "lat": 34.761196,
          "lng": 126.697639,
          "ele": 617.0
        },
        {
          "lat": 34.761758,
          "lng": 126.698929,
          "ele": 635.0
        }
      ],
      "color": "#229d99",
      "start_name": "갈림길 / 목구조목",
      "end_name": "웨이포인트 54",
      "length_meter": 133.6,
      "time_minute": 2
    },
    {
      "path_id": 27,
      "path": [
        {
          "lat": 34.761758,
          "lng": 126.698929,
          "ele": 635.0
        },
        {
          "lat": 34.764099,
          "lng": 126.701088,
          "ele": 673.0
        }
      ],
      "color": "#3f641c",
      "start_name": "웨이포인트 54",
      "end_name": "갈림길",
      "length_meter": 326.6,
      "time_minute": 4
    },
    {
      "path_id": 28,
      "path": [
        {
          "lat": 34.764099,
          "lng": 126.701088,
          "ele": 673.0
        },
        {
          "lat": 34.764507,
          "lng": 126.701385,
          "ele": 688.0
        }
      ],
      "color": "#c3c24e",
      "start_name": "갈림길",
      "end_name": "목구조목",
      "length_meter": 52.9,
      "time_minute": 0
    }
  ]
}